sourceheaders/__init__.py
sourceheaders/__main__.py
sourceheaders/config.py
sourceheaders/default.toml
sourceheaders/main.py
sourceheaders/parser.py
sourceheaders/licenses/AFL-1.1.txt
sourceheaders/licenses/AFL-1.2.txt
sourceheaders/licenses/AFL-2.0.txt
sourceheaders/licenses/AFL-2.1.txt
sourceheaders/licenses/AFL-3.0.txt
sourceheaders/licenses/AGPL-3.0-only.txt
sourceheaders/licenses/AGPL-3.0-or-later.txt
sourceheaders/licenses/AGPL-3.0.txt
sourceheaders/licenses/Apache-2.0.txt
sourceheaders/licenses/BSD-2-Clause.txt
sourceheaders/licenses/BSD-3-Clause.txt
sourceheaders/licenses/BitTorrent-1.0.txt
sourceheaders/licenses/BitTorrent-1.1.txt
sourceheaders/licenses/CUA-OPL-1.0.txt
sourceheaders/licenses/ECL-1.0.txt
sourceheaders/licenses/ECL-2.0.txt
sourceheaders/licenses/GPL-1.0+.txt
sourceheaders/licenses/GPL-1.0-only.txt
sourceheaders/licenses/GPL-1.0-or-later.txt
sourceheaders/licenses/GPL-1.0.txt
sourceheaders/licenses/GPL-2.0+.txt
sourceheaders/licenses/GPL-2.0-only.txt
sourceheaders/licenses/GPL-2.0-or-later.txt
sourceheaders/licenses/GPL-2.0.txt
sourceheaders/licenses/GPL-3.0+.txt
sourceheaders/licenses/GPL-3.0-only.txt
sourceheaders/licenses/GPL-3.0-or-later.txt
sourceheaders/licenses/GPL-3.0.txt
sourceheaders/licenses/Interbase-1.0.txt
sourceheaders/licenses/LGPL-2.0+.txt
sourceheaders/licenses/LGPL-2.0-only.txt
sourceheaders/licenses/LGPL-2.0-or-later.txt
sourceheaders/licenses/LGPL-2.0.txt
sourceheaders/licenses/LGPL-2.1+.txt
sourceheaders/licenses/LGPL-2.1-only.txt
sourceheaders/licenses/LGPL-2.1-or-later.txt
sourceheaders/licenses/LGPL-2.1.txt
sourceheaders/licenses/LGPL-3.0.txt
sourceheaders/licenses/LPPL-1.0.txt
sourceheaders/licenses/LPPL-1.1.txt
sourceheaders/licenses/LPPL-1.2.txt
sourceheaders/licenses/LPPL-1.3a.txt
sourceheaders/licenses/LPPL-1.3c.txt
sourceheaders/licenses/MIT.txt
sourceheaders/licenses/MPL-1.0.txt
sourceheaders/licenses/MPL-1.1.txt
sourceheaders/licenses/MPL-2.0-no-copyleft-exception.txt
sourceheaders/licenses/MPL-2.0.txt
sourceheaders-0.0.1.dist-info/LICENSE
sourceheaders-0.0.1.dist-info/METADATA
sourceheaders-0.0.1.dist-info/WHEEL
sourceheaders-0.0.1.dist-info/entry_points.txt
sourceheaders-0.0.1.dist-info/top_level.txt
sourceheaders-0.0.1.dist-info/RECORD
