Metadata-Version: 2.1
Name: sourceheaders
Version: 0.0.1
Summary: Adds or replaces header comments in source files.
Home-page: https://github.com/Holzhaus/sourceheaders
Author: Jan Holthuis
Author-email: holthuis.jan@googlemail.com
License: MIT
Platform: UNKNOWN
Classifier: Environment :: Console
Classifier: Intended Audience :: Developers
Classifier: License :: OSI Approved :: MIT License
Classifier: Programming Language :: Python :: 3
Classifier: Programming Language :: Python :: 3.10
Classifier: Topic :: Software Development :: Pre-processors
Classifier: Topic :: Software Development :: Quality Assurance
Requires-Python: >=3.10
License-File: LICENSE
Requires-Dist: toml
